upeepz80/__init__.py
upeepz80/peephole.py
upeepz80-0.2.1.dist-info/licenses/LICENSE
upeepz80-0.2.1.dist-info/METADATA
upeepz80-0.2.1.dist-info/WHEEL
upeepz80-0.2.1.dist-info/top_level.txt
upeepz80-0.2.1.dist-info/RECORD
